gumbi/__init__.py
gumbi/aggregation.py
gumbi/array_utils.py
gumbi/arrays.py
gumbi/plotting.py
gumbi/versions.py
gumbi/data/Example_DataSet.pkl
gumbi/data/__init__.py
gumbi/regression/__init__.py
gumbi/regression/base.py
gumbi/regression/botorch/GP.py
gumbi/regression/botorch/__init__.py
gumbi/regression/pymc/GP.py
gumbi/regression/pymc/__init__.py
gumbi/regression/pymc/extras.py
gumbi/style/__init__.py
gumbi/style/breve_presentation.mplstyle
gumbi/style/futura_presentation.mplstyle
gumbi/style/presentation.mplstyle
gumbi/utils/__init__.py
gumbi/utils/generic_utils.py
gumbi/utils/gp_utils.py
gumbi/utils/misc.py
gumbi/utils/pymc_utils.py
tests/__init__.py
tests/conftest.py
tests/test_aggregation.py
tests/test_arrays.py
tests/test_botorch.py
tests/test_plots.py
tests/test_regression.py
gumbi-0.4.0.dist-info/LICENSE
gumbi-0.4.0.dist-info/METADATA
gumbi-0.4.0.dist-info/WHEEL
gumbi-0.4.0.dist-info/top_level.txt
gumbi-0.4.0.dist-info/RECORD
